<annotation verified="no">
  <folder>JPEGImages</folder>
  <filename>002437.jpg</filename>
  <path>D:\workplace\ssd_cosmetic\VOC2007\JPEGImages\000087.jpg</path>
  <source>
    <database>Unknown</database>
  </source>
  <size>
    <width>702</width>
    <height>680</height>
    <depth>3</depth>
  </size>
  <segmented>0</segmented>
  <object>
    <name>cosmetic</name>
    <pose>Unspecified</pose>
    <truncated>0</truncated>
    <Difficult>0</Difficult>
    <bndbox>
      <xmin>242</xmin>
      <ymin>77</ymin>
      <xmax>480</xmax>
      <ymax>586</ymax>
    </bndbox>
  </object>
</annotation>